citeman/__init__.py
citeman/__main__.py
citeman/entry.py
citeman/errors.py
citeman/logo
citeman/prepare.py
citeman/processor.py
citeman/query.py
citeman/ui.py
citeman/ui_history.py
citeman/ui_list.py
citeman/ui_notice.py
citeman/ui_pretty.py
citeman/ui_query.py
citeman/ui_remove.py
citeman/ui_show.py
citeman/utils.py
citeman-0.2.dist-info/LICENSE
citeman-0.2.dist-info/METADATA
citeman-0.2.dist-info/WHEEL
citeman-0.2.dist-info/top_level.txt
citeman-0.2.dist-info/RECORD
