Metadata-Version: 2.1
Name: citeman
Version: 0.2
Summary: A simple command line citation manager for your academic manuscript.
Author-email: "Dylan Russell, MD" <dyl.russell@gmail.com>
Maintainer-email: "Dylan Russell, MD" <dyl.russell@gmail.com>
Project-URL: Homepage, https://github.com/dylanrussellmd/pycite
Project-URL: Issues, https://github.com/dylanrussellmd/pycite/issues
Classifier: Programming Language :: Python :: 3
Classifier: License :: OSI Approved :: MIT License
Classifier: Operating System :: OS Independent
Requires-Python: >=3.8
License-File: LICENSE
Requires-Dist: bibtexparser >=2.0.0b7
Requires-Dist: console-menu
Requires-Dist: ansicolors
Requires-Dist: habanero
